INSTALL.rst
LICENSE
MANIFEST.in
README.rst
VERSION
requirements.txt
setup.py
tasks.py
src/Funspec.egg-info/PKG-INFO
src/Funspec.egg-info/SOURCES.txt
src/Funspec.egg-info/dependency_links.txt
src/Funspec.egg-info/not-zip-safe
src/Funspec.egg-info/requires.txt
src/Funspec.egg-info/top_level.txt
src/funspec/__init__.py
src/funspec/__main__.py
src/funspec/__meta__.py
src/funspec/answer_key.py
src/funspec/arguments.py
src/funspec/base.py
src/funspec/builtins.py
src/funspec/exceptions.py
src/funspec/grader.py
src/funspec/mod.py
src/funspec/result.py
src/funspec/testcase.py
src/funspec/utils.py